micdata/__init__.py
micdata/display.py
micdata/formatting.py
micdata/io.py
micdata/micdata.py
micdata/rollingball.py
micdata/stack.py
micdata-0.1.2.dist-info/LICENSE
micdata-0.1.2.dist-info/METADATA
micdata-0.1.2.dist-info/WHEEL
micdata-0.1.2.dist-info/top_level.txt
micdata-0.1.2.dist-info/RECORD
